elektron_rs-1.0.dist-info/METADATA
elektron_rs-1.0.dist-info/WHEEL
elektron_rs-1.0.dist-info/entry_points.txt
elektron.libs/libxcb-shm-0be6dfbf.so.0
elektron.libs/libidn2-2f4a5893.so.0
elektron.libs/libmount-f4608129.so.1
elektron.libs/libopenjp2-88dcb7ba.so.7
elektron.libs/libdatrie-584ecbbd.so.1
elektron.libs/libpangoft2-1-1fa1613e.0.so.0
elektron.libs/libssl-a3869b75.so.1.1
elektron.libs/libblkid-39d8e54e.so.1
elektron.libs/libpng16-748299c7.so.16
elektron.libs/libnettle-37944285.so.6
elektron.libs/libfontconfig-dcb2ce6c.so.1
elektron.libs/libtiff-c437d1e6.so.5
elektron.libs/libharfbuzz-ff50a4f4.so.0
elektron.libs/libgmp-452f15e0.so.10
elektron.libs/libpangocairo-1-e0e0fbcf.0.so.0
elektron.libs/libxcb-5ddf6756.so.1
elektron.libs/libxcb-render-161c0eb5.so.0
elektron.libs/libpango-1-e80d1584.0.so.0
elektron.libs/libp11-kit-4d4a5b6d.so.0
elektron.libs/libgmodule-2-b0ca77de.0.so.0
elektron.libs/libpcre-0dd207b5.so.1
elektron.libs/libtasn1-222cca92.so.6
elektron.libs/libgraphite2-a2b39163.so.3
elektron.libs/libsmime3-3c89c456.so
elektron.libs/libplc4-5da7697c.so
elektron.libs/liblcms2-2a3d7c52.so.2
elektron.libs/libcairo-gobject-e999f31e.so.2
elektron.libs/libunistring-05abdd40.so.2
elektron.libs/libnspr4-50db7ede.so
elektron.libs/libhogweed-cd4c53be.so.4
elektron.libs/libselinux-64a010fa.so.1
elektron.libs/libpcre2-8-516f4c9d.so.0
elektron.libs/libfribidi-a2ddad26.so.0
elektron.libs/libnssutil3-105f5840.so
elektron.libs/libXau-154567c4.so.6
elektron.libs/libgnutls-0106cf3c.so.30
elektron.libs/libicuuc-14201aad.so.60
elektron.libs/libffi-3a37023a.so.6
elektron.libs/libicudata-05640f77.so.60
elektron.libs/libjbig-2504a0c3.so.2.1
elektron.libs/libplds4-c96adacf.so
elektron.libs/libcairo-dfbea965.so.2
elektron.libs/libuuid-fe2b9824.so.1
elektron.libs/libpoppler-94db9772.so.104
elektron.libs/libjpeg-da649728.so.62
elektron.libs/libcrypto-0a45f796.so.1.1
elektron.libs/libpixman-1-14b1848f.so.0
elektron.libs/libpoppler-glib-405fbbf8.so.8
elektron.libs/libbz2-e34b29ae.so.1
elektron.libs/libthai-cd935638.so.0
elektron.libs/libfreetype-29a7443c.so.6
elektron_rs-1.0.dist-info/RECORD
