Metadata-Version: 2.1
Name: elektron_rs
Version: 1.0
Classifier: Programming Language :: Python :: 3
Requires-Dist: matplotlib
Requires-Dist: matplotlib-backend-kitty
Summary: programmatically create electronic projects
Keywords: electronics,circuit
Author-email: spielhuus <spielhuus@gmail.com>
License: BSD-3-Clause
Requires-Python: >=3.10
